Metadata-Version: 2.4
Name: bald-spider
Version: 0.1.1
Summary: A distributed spider framework
Home-page: https://github.com/6210qwe/SpiderSwarm
Author: MindLullaby
Author-email: 3203939025@qq.com
Classifier: Programming Language :: Python :: 3
Classifier: License :: OSI Approved :: MIT License
Classifier: Operating System :: OS Independent
Requires-Python: >=3.10
Requires-Dist: requests
Requires-Dist: lxml
Requires-Dist: loguru
Requires-Dist: urllib3
Requires-Dist: curl_cffi
Requires-Dist: aiomysql
Requires-Dist: aiohttp
Dynamic: author
Dynamic: author-email
Dynamic: classifier
Dynamic: description
Dynamic: description-content-type
Dynamic: home-page
Dynamic: requires-dist
Dynamic: requires-python
Dynamic: summary
